Metadata-Version: 2.1
Name: coffer-mac
Version: 0.1.1
Summary: Tiny Python API for performing MAC address lookups using Coffer.
Home-page: https://github.com/vesche/coffer_mac
Author: Austin Jackson
Author-email: vesche@protonmail.com
License: MIT
Platform: UNKNOWN
Classifier: Development Status :: 5 - Production/Stable
Classifier: Intended Audience :: Information Technology
Classifier: License :: OSI Approved :: MIT License
Classifier: Programming Language :: Python :: 3
Classifier: Topic :: Security
